miceforest/__init__.py
miceforest/default_lightgbm_parameters.py
miceforest/imputation_kernel.py
miceforest/imputed_data.py
miceforest/logger.py
miceforest/utils.py
miceforest-6.0.3.dist-info/LICENSE
miceforest-6.0.3.dist-info/METADATA
miceforest-6.0.3.dist-info/WHEEL
miceforest-6.0.3.dist-info/top_level.txt
miceforest-6.0.3.dist-info/RECORD
