Metadata-Version: 2.1
Name: miceforest
Version: 6.0.3
Summary: Multiple Imputation by Chained Equations with LightGBM
Author: Sam Von Wilson
License: The MIT License (MIT)
Project-URL: Homepage, https://github.com/AnotherSamWilson/miceforest
Project-URL: Issues, https://github.com/AnotherSamWilson/miceforest/issues
Project-URL: changelog, https://github.com/AnotherSamWilson/miceforest/releases
Classifier: Natural Language :: English
Classifier: Programming Language :: Python :: 3.9
Classifier: Programming Language :: Python :: 3.10
Classifier: Programming Language :: Python :: 3.11
Classifier: License :: OSI Approved :: MIT License
Classifier: Operating System :: OS Independent
License-File: LICENSE
Requires-Dist: lightgbm>=4.1.0
Requires-Dist: pandas>=2.1.0
Requires-Dist: numpy
Requires-Dist: scipy>=1.6.0
Requires-Dist: pyarrow>=6.0.1
Provides-Extra: plotting
Requires-Dist: plotnine>=0.13.6; extra == "plotting"
Requires-Dist: matplotlib>=3.3.0; extra == "plotting"
Provides-Extra: pipeline
Requires-Dist: scikit-learn!=0.22.0; extra == "pipeline"
